gitvenv/__init__.py
gitvenv/__main__.py
gitvenv/gitvenv.py
gitvenv/main_cli.py
gitvenv/scripts/Activate.ps1
gitvenv/scripts/activate
gitvenv-1.0.3.dist-info/LICENSE
gitvenv-1.0.3.dist-info/METADATA
gitvenv-1.0.3.dist-info/WHEEL
gitvenv-1.0.3.dist-info/entry_points.txt
gitvenv-1.0.3.dist-info/top_level.txt
gitvenv-1.0.3.dist-info/RECORD
