Metadata-Version: 2.1
Name: gitvenv
Version: 1.0.3
Summary: Simple tool to create virtual git environments (like a python's venv).
Author-email: Aikawa Yataro <me@aikawayataro.com>
Project-URL: Homepage, https://gitlab.com/yataro/gitvenv
Project-URL: Repository, https://gitlab.com/yataro/gitvenv.git
Project-URL: Issues, https://gitlab.com/yataro/gitvenv/-/issues
Keywords: git,venv
Classifier: Programming Language :: Python :: 3
Classifier: License :: OSI Approved :: MIT License
Classifier: Operating System :: OS Independent
Requires-Python: >=3.8
License-File: LICENSE
